odoo/addons/product_code_regex_validation/README.rst
odoo/addons/product_code_regex_validation/__init__.py
odoo/addons/product_code_regex_validation/__manifest__.py
odoo/addons/product_code_regex_validation/i18n/it.po
odoo/addons/product_code_regex_validation/i18n/product_code_regex_validation.pot
odoo/addons/product_code_regex_validation/models/__init__.py
odoo/addons/product_code_regex_validation/models/product.py
odoo/addons/product_code_regex_validation/models/product_category.py
odoo/addons/product_code_regex_validation/readme/CONTRIBUTORS.rst
odoo/addons/product_code_regex_validation/readme/DESCRIPTION.rst
odoo/addons/product_code_regex_validation/readme/USAGE.rst
odoo/addons/product_code_regex_validation/static/description/icon.png
odoo/addons/product_code_regex_validation/static/description/index.html
odoo/addons/product_code_regex_validation/tests/__init__.py
odoo/addons/product_code_regex_validation/tests/test_product_code_regex_validation.py
odoo/addons/product_code_regex_validation/views/product_category.xml
odoo_addon_product_code_regex_validation-16.0.1.0.0.4.dist-info/METADATA
odoo_addon_product_code_regex_validation-16.0.1.0.0.4.dist-info/WHEEL
odoo_addon_product_code_regex_validation-16.0.1.0.0.4.dist-info/top_level.txt
odoo_addon_product_code_regex_validation-16.0.1.0.0.4.dist-info/RECORD
